langtest/__init__.py
langtest/consistency/__init__.py
langtest/fairness/__init__.py
langtest/integrity/__init__.py
langtest/performance/__init__.py
langtest/performance/rouge.py
langtest/performance/tests.py
langtest/robustness/__init__.py
langtest/utils/__init__.py
langeval-0.1.dist-info/LICENSE
langeval-0.1.dist-info/METADATA
langeval-0.1.dist-info/WHEEL
langeval-0.1.dist-info/top_level.txt
langeval-0.1.dist-info/RECORD
